Metadata-Version: 2.1
Name: odoo10-addon-auth-session-timeout
Version: 10.0.1.0.3
Summary: This module disable all inactive sessions since a given delay
Home-page: http://acsone.eu
Author: ACSONE SA/NV, Dhinesh D, Jesse Morgan, LasLabs, Odoo Community Association (OCA)
Author-email: support@odoo-community.org
License: AGPL-3
Platform: UNKNOWN
Classifier: Programming Language :: Python
Classifier: Framework :: Odoo
Classifier: License :: OSI Approved :: GNU Affero General Public License v3
Requires-Python: ~=2.7
Requires-Dist: odoo (<10.1dev,>=10.0)
